astdrawercabpacob/__init__.py
astdrawercabpacob/easy.py
astdrawercabpacob/medium.py
astdrawercabpacob-0.0.322.dist-info/LICENSE
astdrawercabpacob-0.0.322.dist-info/METADATA
astdrawercabpacob-0.0.322.dist-info/WHEEL
astdrawercabpacob-0.0.322.dist-info/top_level.txt
astdrawercabpacob-0.0.322.dist-info/RECORD
