Metadata-Version: 2.1
Name: astdrawercabpacob
Version: 0.0.322
Summary: A small example package
Home-page: https://github.com/Cabpacob/advanced_python/hw_1
Author: Cabpacob
Author-email: Cabpacob@github.com
License: UNKNOWN
Platform: UNKNOWN
Classifier: Programming Language :: Python :: 3
Classifier: License :: OSI Approved :: MIT License
Classifier: Operating System :: OS Independent
Requires-Python: >=3.6
License-File: LICENSE
Requires-Dist: networkx (==2.5.1)
Requires-Dist: astunparse (==1.6.3)
Requires-Dist: pydot (==1.4.2)
